{
  "type": "Photo",
  "mag_data": { "samples":[[100, 100, 100]] },
  "trigger": "RTC",
  "fw_version": "v1.5.6-0-gc109663",
  "system_version": "v0.100.3-0-gd0517f0",
  "hw_rev": "Clip2 Rev1D",
  "avg_win": [50, 50, 50, 50, 50, 50, 50, 50, 50, 50, 50, 50, 50, 50, 50, 50 ], 
  "aec_gain": 256, 
  "aec_exp": 16, 
  "state_of_charge": 81, 
  "voltage": 3861, 
  "avg_readout": 50, 
  "light_meter": 768, 
  "too_dark": 0, 
  "image_seq": 3267, 
  "sess_seq": 234, 
  "acc_data": { "samples":[[14469, -2437, 7237]],
                  "now":[14776, -2264, 7544],
                  "std":[236, 315, 363] },
  "awb_gain": [5426, 4096, 12302] 
}
