{
  "type": "Photo",
  "mag_data": { "samples":[[100, 100, 100]] },
  "trigger": "RTC",
  "fw_version": "v1.5.6-0-gc109663",
  "system_version": "v0.100.3-0-gd0517f0",
  "hw_rev": "Clip2 Rev1D",
  "avg_win": [50, 50, 50, 50, 50, 50, 50, 50, 50, 50, 50, 50, 50, 50, 50, 50 ], 
  "aec_gain": 256, 
  "aec_exp": 16, 
  "state_of_charge": 52, 
  "voltage": 3746, 
  "avg_readout": 50, 
  "light_meter": 768, 
  "too_dark": 0, 
  "image_seq": 3726, 
  "sess_seq": 686, 
  "acc_data": { "samples":[[12909, 3483, -9087]],
                  "now":[12956, 3464, -9180],
                  "std":[100, 59, 68] },
  "awb_gain": [6258, 4096, 7375] 
}
