{
  "type": "Photo",
  "mag_data": { "samples":[[100, 100, 100]] },
  "trigger": "RTC",
  "fw_version": "v1.5.6-0-gc109663",
  "system_version": "v0.100.3-0-gd0517f0",
  "hw_rev": "Clip2 Rev1D",
  "avg_win": [50, 50, 50, 50, 50, 50, 50, 50, 50, 50, 50, 50, 50, 50, 50, 50 ], 
  "aec_gain": 256, 
  "aec_exp": 16, 
  "state_of_charge": 76, 
  "voltage": 3843, 
  "avg_readout": 50, 
  "light_meter": 768, 
  "too_dark": 0, 
  "image_seq": 5308, 
  "sess_seq": 277, 
  "acc_data": { "samples":[[11912, -5838, 8989]],
                  "now":[10400, -7628, 8880],
                  "std":[2191, 2079, 0] },
  "awb_gain": [6656, 4096, 8058] 
}
