{
  "type": "Photo",
  "mag_data": { "samples":[[100, 100, 100]] },
  "trigger": "RTC",
  "fw_version": "v1.5.6-0-gc109663",
  "system_version": "v0.100.3-0-gd0517f0",
  "hw_rev": "Clip2 Rev1D",
  "avg_win": [50, 50, 50, 50, 50, 50, 50, 50, 50, 50, 50, 50, 50, 50, 50, 50 ], 
  "aec_gain": 256, 
  "aec_exp": 16, 
  "state_of_charge": 66, 
  "voltage": 3794, 
  "avg_readout": 50, 
  "light_meter": 768, 
  "too_dark": 0, 
  "image_seq": 4876, 
  "sess_seq": 1918, 
  "acc_data": { "samples":[[11493, -10953, 2892]],
                  "now":[11520, -10916, 2788],
                  "std":[217, 84, 314] },
  "awb_gain": [7303, 4096, 7432] 
}
