{"aps": [{"mac": "e0:8e:3c:28:78:60","age": 0,"level": -52,"freq": 2412},{"mac": "e0:8e:3c:32:81:02","age": 0,"level": -57,"freq": 2437},{"mac": "10:be:f5:1c:76:6c","age": 0,"level": -75,"freq": 2412},{"mac": "e8:de:27:3e:51:9a","age": 0,"level": -82,"freq": 2427},{"mac": "40:16:7e:a4:02:e0","age": 0,"level": -63,"freq": 2437},{"mac": "e0:8e:3c:04:03:08","age": 0,"level": -77,"freq": 2437},{"mac": "00:26:75:7f:48:7a","age": 0,"level": -81,"freq": 2437},{"mac": "00:26:75:ec:be:74","age": 0,"level": -74,"freq": 2427},{"mac": "60:45:cb:8f:7d:40","age": 0,"level": -52,"freq": 2452},{"mac": "64:70:02:39:5d:b8","age": 0,"level": -73,"freq": 2462},{"mac": "48:8d:36:c3:61:ce","age": 0,"level": -87,"freq": 2462},{"mac": "48:8d:36:ac:a4:a0","age": 0,"level": -89,"freq": 2427},{"mac": "00:26:75:e4:52:d0","age": 0,"level": -78,"freq": 2437},{"mac": "00:26:75:b0:73:09","age": 0,"level": -83,"freq": 2432},{"mac": "e0:8e:3c:14:0d:f1","age": 0,"level": -80,"freq": 2437},{"mac": "10:7b:44:3d:20:c8","age": 0,"level": -80,"freq": 2447},{"mac": "bc:ee:7b:55:d0:d6","age": 0,"level": -82,"freq": 2447},{"mac": "00:26:75:c4:ce:97","age": 0,"level": -85,"freq": 2462}]}
