{
  "type": "Photo",
  "mag_data": { "samples":[[100, 100, 100]] },
  "trigger": "RTC",
  "fw_version": "v1.5.6-0-gc109663",
  "system_version": "v0.100.3-0-gd0517f0",
  "hw_rev": "Clip2 Rev1D",
  "avg_win": [50, 50, 50, 50, 50, 50, 50, 50, 50, 50, 50, 50, 50, 50, 50, 50 ], 
  "aec_gain": 256, 
  "aec_exp": 16, 
  "state_of_charge": 73, 
  "voltage": 3874, 
  "avg_readout": 50, 
  "light_meter": 768, 
  "too_dark": 0, 
  "image_seq": 2820, 
  "sess_seq": 184, 
  "acc_data": { "samples":[[15067, -5663, -1880]],
                  "now":[14464, -5304, 808],
                  "std":[249, 305, 1063] },
  "awb_gain": [6515, 4096, 8401] 
}
